{
  "methodology_version": "1.0.5",
  "generated_at": "2026-05-24T15:36:25.085154Z",
  "data_license": "CC-BY 4.0",
  "attribution": "Data: NASA FIRMS, ESA Copernicus, ACLED. Analysis: WCED v1.0.5",
  "event_id": "b11e03f6-53b0-4379-93ad-6049b0b88469",
  "chain": [
    {
      "node_type": "computation",
      "id": "c314ec58-8fb7-5b53-83b9-25e9f45c84e1",
      "detail": {
        "produced_by": "wced.quantify.frp",
        "method": "frp_to_co2_v1.0.5",
        "confidence_label": "REPORTED",
        "produced_at": "2026-05-24T09:14:35.508953+00:00",
        "notes": null
      }
    },
    {
      "node_type": "computation",
      "id": "bed2152f-113b-4de5-af8f-119f524245e7",
      "detail": {
        "produced_by": "wced.detect.hotspot",
        "method": "firms_clustering_v1",
        "confidence_label": "REPORTED",
        "produced_at": "2026-03-07T06:24:00+00:00",
        "notes": null
      }
    },
    {
      "node_type": "computation",
      "id": "43152cef-1510-50be-a799-25579f457e6e",
      "detail": {
        "produced_by": "wced.detect.baseline",
        "method": "rolling_p75_baseline_v1.0.1",
        "confidence_label": "REPORTED",
        "produced_at": "2026-05-23T00:35:00+00:00",
        "notes": null
      }
    },
    {
      "node_type": "source",
      "id": "de10f583-1d25-4682-999b-eac9e9d39e52",
      "detail": {
        "source_type": "SATELLITE",
        "identifier": "NASA FIRMS detections for facility Aghajari oil field",
        "retrieved_at": "2026-05-24T11:45:42.973020+00:00"
      }
    }
  ],
  "rendered": "[COMPUTATION] wced.quantify.frp / frp_to_co2_v1.0.5 [REPORTED]\n\u2192 [COMPUTATION] wced.detect.hotspot / firms_clustering_v1 [REPORTED]\n\u2192 [COMPUTATION] wced.detect.baseline / rolling_p75_baseline_v1.0.1 [REPORTED]\n\u2192 [SATELLITE] NASA FIRMS detections for facility Aghajari oil field"
}